{
  "code": "sM.itemPetEst",
  "orderNumber": 19,
  "type": 1,
  "title": "",
  "caption": "Заявления",
  "classname": "petitionEstimated",
  "container": null,
  "collection": null,
  "url": null,
  "hint": null,
  "conditions": [{
    "property": null,
    "operation": 0,
    "value": null,
    "nestedConditions": [{
        "property": "status",
        "operation": 1,
        "value": [
          "23"
        ],
        "nestedConditions": []
      },
      {
        "property": "status",
        "operation": 1,
        "value": [
          "27"
        ],
        "nestedConditions": []
      },
      {
        "property": "status",
        "operation": 1,
        "value": [
          "25"
        ],
        "nestedConditions": []
      }
    ]
  }],
  "eagerLoading": {
    "exportItem": {
      "petitionEstimated@khv-gosekspertiza": ["customerOrg",
        "customerOrg.bankAccount",
        "customerOrg.staff",
        "customerOrg.legalAdr",
        "docFormCont",
        "expObject",
        "expObject.address",
        "executorIzA.izOrgExecutor",
        "executorIzA.izOrgExecutor.legalAdr",
        "executorPdA.pdOrgExecutor",
        "executorPdA.pdOrgExecutor.legalAdr",
        "developOrg",
        "developOrg.legalAdr",
        "customerOrgObj",
        "customerOrgObj.legalAdr",
        "developOrg",
        "executorPdA.pdOrgExecutor",
        "contractEstimated",
        "contractEstimated.bankAccount",
        "inspectionEstimate",
        "inspectionEstimate.expEmployee",
        "inspectionEstimate.result"
      ]
    }
  },
  "sorting": [],
  "pathChains": []
}